spidery/__init__.py
spidery/spidery.py
spidery/__tests__/e2e_withAuth/__init__.py
spidery/__tests__/e2e_withAuth/test.py
spidery/__tests__/v1/e2e_withAuth/__init__.py
spidery/__tests__/v1/e2e_withAuth/test.py
spidery_py-1.10.2.dist-info/LICENSE
spidery_py-1.10.2.dist-info/METADATA
spidery_py-1.10.2.dist-info/WHEEL
spidery_py-1.10.2.dist-info/top_level.txt
spidery_py-1.10.2.dist-info/RECORD
