Metadata-Version: 2.2
Name: spidery-py
Version: 1.10.2
Summary: Python SDK for Spidery API
Home-page: https://github.com/khulnasoft/spidery
Author: Khulnasoft.com
Author-email: "Khulnasoft.com" <nick@khulnasoft.com>
Maintainer-email: "Khulnasoft.com" <nick@khulnasoft.com>
License: GNU Affero General Public License v3 (AGPLv3)
Project-URL: Documentation, https://docs.spidery.khulnasoft.com
Project-URL: Source, https://github.com/khulnasoft/spidery
Project-URL: Tracker, https://github.com/khulnasoft/spidery/issues
Keywords: SDK,API,spidery
Classifier: Development Status :: 5 - Production/Stable
Classifier: Environment :: Web Environment
Classifier: Intended Audience :: Developers
Classifier: License :: OSI Approved :: GNU General Public License v3 (GPLv3)
Classifier: Natural Language :: English
Classifier: Operating System :: OS Independent
Classifier: Programming Language :: Python
Classifier: Programming Language :: Python :: 3
Classifier: Programming Language :: Python :: 3.8
Classifier: Programming Language :: Python :: 3.9
Classifier: Programming Language :: Python :: 3.10
Classifier: Topic :: Internet
Classifier: Topic :: Internet :: WWW/HTTP
Classifier: Topic :: Internet :: WWW/HTTP :: Indexing/Search
Classifier: Topic :: Software Development
Classifier: Topic :: Software Development :: Libraries
Classifier: Topic :: Software Development :: Libraries :: Python Modules
Classifier: Topic :: Text Processing
Classifier: Topic :: Text Processing :: Indexing
Requires-Python: >=3.8
License-File: LICENSE
Requires-Dist: requests
Requires-Dist: python-dotenv
Requires-Dist: websockets
Requires-Dist: nest-asyncio
Requires-Dist: pydantic>=2.10.3
Dynamic: author
Dynamic: home-page
Dynamic: requires-python
